debits/__init__.py
debits/debits_base/__init__.py
debits/debits_base/base.py
debits/debits_base/models.py
debits/debits_base/processors.py
debits/debits_base/fixtures/processors.json
debits/debits_base/migrations/0001_initial.py
debits/debits_base/migrations/__init__.py
debits/debits_test/__init__.py
debits/debits_test/business.py
debits/debits_test/callbacks.py
debits/debits_test/forms.py
debits/debits_test/local_settings.py
debits/debits_test/models.py
debits/debits_test/processors.py
debits/debits_test/products.py
debits/debits_test/test_settings.py
debits/debits_test/urls.py
debits/debits_test/views.py
debits/debits_test/wsgi.py
debits/debits_test/migrations/0001_initial.py
debits/debits_test/migrations/__init__.py
debits/paypal/__init__.py
debits/paypal/form.py
debits/paypal/models.py
debits/paypal/views.py
debits/paypal/migrations/0001_initial.py
debits/paypal/migrations/0002_auto_20190507_1600.py
debits/paypal/migrations/__init__.py
django_debits-0.1.15.dist-info/LICENSE.txt
django_debits-0.1.15.dist-info/METADATA
django_debits-0.1.15.dist-info/WHEEL
django_debits-0.1.15.dist-info/top_level.txt
django_debits-0.1.15.dist-info/RECORD
