Metadata-Version: 2.1
Name: django-debits
Version: 0.1.15
Summary: Accepting payments
Home-page: http://freesoft.portonvictor.org/django-debits.xml
Author: Victor Porton
Author-email: porton@narod.ru
License: AGPLv3+
Keywords: payment paypal
Platform: UNKNOWN
Classifier: Development Status :: 4 - Beta
Classifier: Intended Audience :: Developers
Classifier: Topic :: Software Development :: Libraries :: Python Modules
Classifier: License :: OSI Approved :: GNU Affero General Public License v3 or later (AGPLv3+)
Classifier: Programming Language :: Python :: 3
Classifier: Programming Language :: Python :: 3.3
Classifier: Programming Language :: Python :: 3.4
Classifier: Programming Language :: Python :: 3.5
Classifier: Programming Language :: Python :: 3.6
Classifier: Programming Language :: Python :: 3.7
